LICENSE
MANIFEST.in
README.md
setup.py
stepz/__init__.py
stepz.egg-info/PKG-INFO
stepz.egg-info/SOURCES.txt
stepz.egg-info/dependency_links.txt
stepz.egg-info/requires.txt
stepz.egg-info/top_level.txt
stepz.egg-info/zip-safe