Metadata-Version: 2.1
Name: stepz
Version: 0.14
Summary: Easy parser for parse template $variable
Home-page: https://github.com/hanzhichao/stepz
Author: Han Zhichao
Author-email: superhin@126.com
License: MIT license
Keywords: stepz,step runnser,step pipline
Platform: UNKNOWN
Classifier: Programming Language :: Python
Classifier: Programming Language :: Python :: 2.7
Classifier: Programming Language :: Python :: 3.7
